smnsr/__init__.py
smnsr/cross_validate.py
smnsr/logging.yaml
smnsr/modalities/modalities.yaml
smnsr/models/__init__.py
smnsr/models/base_model.py
smnsr/models/base_stacked_model.py
smnsr/models/knn.py
smnsr/models/regression.py
smnsr/patients/AugmentedTADPOLEData.py
smnsr/patients/TADPOLEData.py
smnsr/patients/__init__.py
smnsr/patients/timeseries_creation.py
smnsr-0.4.51.data/scripts/smnsr_cv
smnsr-0.4.51.data/scripts/smnsr_merge
smnsr-0.4.51.data/scripts/smnsr_ts_folds
tests/__init__.py
tests/test_AugmentedTADPOLEData.py
tests/test_KNNSR.py
tests/test_TADPOLEData.py
tests/test_cross_validate.py
tests/test_regression.py
tests/test_timeseries_creation.py
smnsr-0.4.51.dist-info/LICENSE
smnsr-0.4.51.dist-info/METADATA
smnsr-0.4.51.dist-info/WHEEL
smnsr-0.4.51.dist-info/top_level.txt
smnsr-0.4.51.dist-info/RECORD
