Metadata-Version: 2.1
Name: smnsr
Version: 0.4.51
Summary: SMNSR
Home-page: https://github.com/rciszek/SMNSR/
Author: rciszek
Author-email: rkciszek@gmail.com
License: UNKNOWN
Platform: UNKNOWN
Classifier: Development Status :: 2 - Pre-Alpha
Classifier: Environment :: Console
Classifier: Intended Audience :: Science/Research
Classifier: License :: OSI Approved :: MIT License
Classifier: Programming Language :: Python :: 3
Classifier: Programming Language :: Python :: 3.7
Requires-Python: >=3.7
Requires-Dist: PySocks (>=1.7.1)
Requires-Dist: pandas (>=1.0.5)
Requires-Dist: matplotlib (>=3.2.2)
Requires-Dist: scipy (>=1.4.1)
Requires-Dist: xgboost (>=1.1.1)
Requires-Dist: psutil (>=5.7.0)
Requires-Dist: ray (>=0.8.4)
Requires-Dist: vaex-core (>=2.0.3)
Requires-Dist: pytictoc (>=1.5.0)
Requires-Dist: gdown (>=3.11.1)
Requires-Dist: numpy (>=1.18.4)
Requires-Dist: seaborn (>=0.10.1)
Requires-Dist: python-dateutil (>=2.8.1)
Requires-Dist: PyYAML (>=5.3.1)
Requires-Dist: scikit-learn (>=0.23.1)
Requires-Dist: vaex (>=3.0.0)
